odoo/addons/stock_orderpoint_manual_procurement_uom/README.rst
odoo/addons/stock_orderpoint_manual_procurement_uom/__init__.py
odoo/addons/stock_orderpoint_manual_procurement_uom/__manifest__.py
odoo/addons/stock_orderpoint_manual_procurement_uom/i18n/stock_orderpoint_manual_procurement_uom.pot
odoo/addons/stock_orderpoint_manual_procurement_uom/i18n/zh_CN.po
odoo/addons/stock_orderpoint_manual_procurement_uom/models/__init__.py
odoo/addons/stock_orderpoint_manual_procurement_uom/models/stock_warehouse_orderpoint.py
odoo/addons/stock_orderpoint_manual_procurement_uom/readme/CONTRIBUTORS.rst
odoo/addons/stock_orderpoint_manual_procurement_uom/readme/DESCRIPTION.rst
odoo/addons/stock_orderpoint_manual_procurement_uom/readme/USAGE.rst
odoo/addons/stock_orderpoint_manual_procurement_uom/static/description/icon.png
odoo/addons/stock_orderpoint_manual_procurement_uom/static/description/index.html
odoo/addons/stock_orderpoint_manual_procurement_uom/tests/__init__.py
odoo/addons/stock_orderpoint_manual_procurement_uom/tests/test_stock_orderpoint_manual_procurement.py
odoo/addons/stock_orderpoint_manual_procurement_uom/wizards/__init__.py
odoo/addons/stock_orderpoint_manual_procurement_uom/wizards/make_procurement_orderpoint.py
odoo13_addon_stock_orderpoint_manual_procurement_uom-13.0.1.0.1.dev4.dist-info/METADATA
odoo13_addon_stock_orderpoint_manual_procurement_uom-13.0.1.0.1.dev4.dist-info/WHEEL
odoo13_addon_stock_orderpoint_manual_procurement_uom-13.0.1.0.1.dev4.dist-info/top_level.txt
odoo13_addon_stock_orderpoint_manual_procurement_uom-13.0.1.0.1.dev4.dist-info/RECORD
